viggofiscal/__init__.py
viggofiscal/_version.py
viggofiscal/resources.py
viggofiscal/subsystem/__init__.py
viggofiscal/subsystem/calculo_fiscal/__init__.py
viggofiscal/subsystem/calculo_fiscal/utils.py
viggofiscal/subsystem/calculo_fiscal/icms/__init__.py
viggofiscal/subsystem/calculo_fiscal/icms/base_icms_proprio.py
viggofiscal/subsystem/calculo_fiscal/icms/base_icms_st.py
viggofiscal/subsystem/calculo_fiscal/icms/base_reduzida_icms_proprio.py
viggofiscal/subsystem/calculo_fiscal/icms/base_reduzida_icms_st.py
viggofiscal/subsystem/calculo_fiscal/icms/icms00.py
viggofiscal/subsystem/calculo_fiscal/icms/icms10.py
viggofiscal/subsystem/calculo_fiscal/icms/icms101.py
viggofiscal/subsystem/calculo_fiscal/icms/icms20.py
viggofiscal/subsystem/calculo_fiscal/icms/icms201.py
viggofiscal/subsystem/calculo_fiscal/icms/icms202_203.py
viggofiscal/subsystem/calculo_fiscal/icms/icms30.py
viggofiscal/subsystem/calculo_fiscal/icms/icms51.py
viggofiscal/subsystem/calculo_fiscal/icms/icms70.py
viggofiscal/subsystem/calculo_fiscal/icms/icms90.py
viggofiscal/subsystem/calculo_fiscal/icms/icms900.py
viggofiscal/subsystem/calculo_fiscal/icms/valor_icms_proprio.py
viggofiscal/subsystem/calculo_fiscal/icms/valor_icms_st.py
viggofiscal/subsystem/calculo_fiscal/ipi/__init__.py
viggofiscal/subsystem/calculo_fiscal/ipi/base_ipi.py
viggofiscal/subsystem/calculo_fiscal/ipi/ipi50_ad_valorem.py
viggofiscal/subsystem/calculo_fiscal/ipi/ipi50_especifico.py
viggofiscal/subsystem/calculo_fiscal/pis/__init__.py
viggofiscal/subsystem/calculo_fiscal/pis/base_pis.py
viggofiscal/subsystem/calculo_fiscal/pis/pis_cofins01_02.py
viggofiscal/subsystem/calculo_fiscal/pis/pis_cofins03.py
viggofiscal/subsystem/financeiro/__init__.py
viggofiscal/subsystem/financeiro/centro_resultado/__init__.py
viggofiscal/subsystem/financeiro/centro_resultado/manager.py
viggofiscal/subsystem/financeiro/centro_resultado/resource.py
viggofiscal/subsystem/financeiro/conta_dre/__init__.py
viggofiscal-1.8.2.dist-info/AUTHORS
viggofiscal-1.8.2.dist-info/METADATA
viggofiscal-1.8.2.dist-info/WHEEL
viggofiscal-1.8.2.dist-info/top_level.txt
viggofiscal-1.8.2.dist-info/RECORD
