Metadata-Version: 2.1
Name: viggofiscal
Version: 1.8.2
Summary: ViggoFiscal Backend Flask REST service
Home-page: https://gitlab.com/0RT1/viggofiscal-backend.git
License: UNKNOWN
Platform: UNKNOWN
License-File: AUTHORS
Requires-Dist: viggocore<2.0.0,>=1.0.0
Requires-Dist: viggolocal>=1.0.0
Requires-Dist: flask-cors
